<observatory>
  <shortName></shortName>
  <fullName></fullName>
  <latitude></latitude>
  <numAntennas></numAntennas>
  <antennaDiameter></antennaDiameter>
  <elevationLimit></elevationLimit>
  <configurationList>
	 <configuration>
		<name></name>
	 </configuration>
  </configurationList>
  <stations></stations>
  <tracks></tracks>
  <referenceLocation></referenceLocation>
</observatory>

<observatory>
  <shortName>ATCA</shortName>
  <fullName>Australian Telescope Compact Array</fullName>
  <latitude>-0.529059644</latitude>
  <numAntennas>6</numAntennas>
  <antennaDiameter>22.0</antennaDiameter>
  <elevationLimit></elevationLimit>
  <configurationList>
	 <configuration>
		<name>6A</name>
		3, 11, 16, 30, 34, 37
	 </configuration>
	 <configuration>
		<name>6B</name>
		2, 12, 25, 31, 35, 37
	 </configuration>	
	 <configuration>	
		<name>6C</name>
		1,  6, 21, 24, 31, 37
	 </configuration>	 
	 <configuration>
		<name>6D</name>
		5, 10, 13, 28, 30, 37
	 </configuration>
	 <configuration>
		<name>1.5A</name>
		15, 18, 25, 28, 35, 37
	 </configuration>
	 <configuration>
		<name>1.5B</name>
		19, 21, 27, 31, 34, 37
	 </configuration>	 
	 <configuration>
		<name>1.5C</name>
		14, 22, 30, 33, 34, 37
	 </configuration>
	 <configuration>	
		<name>1.5D</name>
		16, 17, 24, 31, 35, 37
	 </configuration>	 
	 <configuration>
		<name>750A</name>
		25, 27, 29, 33, 34, 37
	 </configuration>
	 <configuration>
		<name>750B</name>
		14, 17, 21, 24, 26, 37
	 </configuration>
	 <configuration>	 
		<name>750C</name>
		12, 13, 15, 18, 21, 37
	 </configuration>
	 <configuration>	 
		<name>750D</name>
		15, 16, 22, 24, 25, 37
	 </configuration>
	 <configuration>	 
		<name>375</name>
		2,  6,  8,  9, 10, 37
	 </configuration>
	 <configuration>	 
		<name>210</name>
		14, 15, 16, 17, 20, 37
	 </configuration>
	 <configuration>	 
		<name>122B</name>
		5,  6,  7,  8,  9, 37
	 </configuration>
  </configurationList>
  <stations></stations>
  <tracks></tracks>
  <referenceLocation></referenceLocation>
  <configurationNames></configurationNames>
</observatory>
